rshogi_migration/__init__.py
rshogi-0.2.0.dist-info/METADATA
rshogi-0.2.0.dist-info/WHEEL
rshogi-0.2.0.dist-info/top_level.txt
rshogi-0.2.0.dist-info/RECORD
