Metadata-Version: 2.4
Name: rshogi
Version: 0.2.0
Summary: Migration shim: installs rshogi-py. The import name remains `rshogi`.
Author: rshogi contributors
License: MIT
Classifier: Programming Language :: Python :: 3
Classifier: License :: OSI Approved :: MIT License
Classifier: Operating System :: OS Independent
Requires-Python: >=3.9
Requires-Dist: rshogi-py>=0.2.0
